kafkaHelper/__init__.py
kafkaHelper/kafkaHelper.py
tests/__init__.py
tests/kafka_Helper_tests.py
KafkaHelper_athanikos-0.2.9.dist-info/LICENSE
KafkaHelper_athanikos-0.2.9.dist-info/METADATA
KafkaHelper_athanikos-0.2.9.dist-info/WHEEL
KafkaHelper_athanikos-0.2.9.dist-info/top_level.txt
KafkaHelper_athanikos-0.2.9.dist-info/RECORD
