Metadata-Version: 2.1
Name: KafkaHelper-athanikos
Version: 0.2.9
Summary: A set of helper to produce / consume from / to kafka (uses kafka-python)
Home-page: UNKNOWN
Author: Nikos Athanasakis
Author-email: athanikos@gmail.com
License: MIT License
Platform: UNKNOWN
Classifier: Development Status :: 1 - Planning
Classifier: License :: OSI Approved :: MIT License
Classifier: Operating System :: OS Independent
